GOT/__init__.py
GOT/data/__init__.py
GOT/data/base_dataset.py
GOT/data/conversation_dataset_qwen.py
GOT/demo/process_results.py
GOT/demo/run_ocr_2.0.py
GOT/demo/run_ocr_2.0_crop.py
GOT/demo/test_demo.py
GOT/demo/test_latex2html2md.py
GOT/demo/test_run_ocr_2.0.py
GOT/demo/test_run_ocr_2.0_crop.py
GOT/eval/eval_GOT_ocr.py
GOT/eval/evaluate_GOT.py
GOT/eval/multi_hardware_eval_GOT.py
GOT/eval/pyevaltools/__init__.py
GOT/eval/pyevaltools/eval_ocr.py
GOT/eval/pyevaltools/eval_ocr_format.py
GOT/eval/pyevaltools/eval_ocr_scene.py
GOT/eval/pyevaltools/merge_results.py
GOT/model/GOT_ocr_2_0.py
GOT/model/__init__.py
GOT/model/plug/blip_process.py
GOT/model/vision_encoder/__init__.py
GOT/model/vision_encoder/vary_b.py
GOT/train/train.py
GOT/train/train_GOT.py
GOT/train/train_flash_attn.py
GOT/train/train_lora.py
GOT/train/train_lora_flash_attn.py
GOT/train/trainer.py
GOT/train/trainer_llm_llrd.py
GOT/train/trainer_vit_fixlr.py
GOT/train/trainer_vit_llrd.py
GOT/utils/arguments.py
GOT/utils/constants.py
GOT/utils/conversation.py
GOT/utils/utils.py
stepGOT-0.1.0.dist-info/METADATA
stepGOT-0.1.0.dist-info/WHEEL
stepGOT-0.1.0.dist-info/top_level.txt
stepGOT-0.1.0.dist-info/RECORD
